tests/__init__.py
tests/test_dataConverter.py
tests/test_energyConverter.py
tests/test_lengthConverter.py
tests/test_massConverter.py
tests/test_pressureConverter.py
tests/test_speedConverter.py
tests/test_tempConverter.py
tests/test_timeConverter.py
tests/test_volumeConverter.py
unitize/__init__.py
unitize/data_storage.py
unitize/energy.py
unitize/frequency.py
unitize/history.py
unitize/length.py
unitize/mass.py
unitize/pressure.py
unitize/speed.py
unitize/temperature.py
unitize/time.py
unitize/util.py
unitize/volume.py
unitize-0.0.7.dist-info/LICENSE.txt
unitize-0.0.7.dist-info/METADATA
unitize-0.0.7.dist-info/WHEEL
unitize-0.0.7.dist-info/top_level.txt
unitize-0.0.7.dist-info/RECORD
