Metadata-Version: 2.1
Name: unitize
Version: 0.0.7
Summary: A package for unit conversion and casting.
Home-page: UNKNOWN
Author: Naren Dawar
License: UNKNOWN
Keywords: python,conversion,units,data,time,data conversion
Platform: UNKNOWN
Classifier: Intended Audience :: Education
Classifier: Programming Language :: Python :: 2
Classifier: Programming Language :: Python :: 3
Classifier: Operating System :: MacOS :: MacOS X
Classifier: Operating System :: Microsoft :: Windows
